ansible_cached_lookup.py
ansible_cached_lookup-1.0.0.dist-info/METADATA
ansible_cached_lookup-1.0.0.dist-info/RECORD
ansible_cached_lookup-1.0.0.dist-info/WHEEL
ansible_cached_lookup-1.0.0.dist-info/top_level.txt
