Metadata-Version: 2.1
Name: ansible-cached-lookup
Version: 1.0.0
Summary: An Ansible lookup plugin that caches the result of any other lookup
Home-page: UNKNOWN
License: MIT
Platform: UNKNOWN
Classifier: Intended Audience :: Developers
Classifier: Programming Language :: Python
Classifier: Programming Language :: Python :: 2.7
Classifier: Programming Language :: Python :: 3
Classifier: Programming Language :: Python :: 3.6
Classifier: Programming Language :: Python :: 3.7
Classifier: License :: OSI Approved :: MIT License
Requires-Dist: ansible
Requires-Dist: diskcache
